ponodo/abc/__init__.py
ponodo/abc/container.py
ponodo/console/__init__.py
ponodo/console/commands.py
ponodo/core.py
ponodo/database/__init__.py
ponodo/database/migration.py
ponodo/database/model.py
ponodo/database/model.pyi
ponodo/database/query.py
ponodo/helpers.py
ponodo/http.py
ponodo/routing/__init__.py
ponodo/routing/controller_dispatcher.py
ponodo/routing/route.py
ponodo-0.1.0a1.dist-info/WHEEL
ponodo-0.1.0a1.dist-info/METADATA
ponodo-0.1.0a1.dist-info/RECORD
