Metadata-Version: 2.1
Name: ponodo
Version: 0.1.0a1
Summary: Web Application Framework for Pythonista
Author: Fathur Rohman
Author-email: hi.fathur.rohman@gmail.com
Requires-Python: >=3.10,<4.0
Classifier: Programming Language :: Python :: 3
Classifier: Programming Language :: Python :: 3.10
Requires-Dist: Werkzeug (>=2.2.1,<3.0.0)
Requires-Dist: click (>=8.1.3,<9.0.0)
Requires-Dist: inflect (>=6.0.0,<7.0.0)
Requires-Dist: ipython (>=8.4.0,<9.0.0)
